{
  "background": {
    "value": "{mint.7}",
    "type": "color"
  },
  "surface": {
    "value": "{mint.6}",
    "type": "color"
  },
  "border": {
    "value": "{mint.5}",
    "type": "color"
  },
  "on-low": {
    "value": "{mint.4}",
    "type": "color"
  },
  "on-mid": {
    "value": "{mint.3}",
    "type": "color"
  },
  "on": {
    "value": "{mint.0}",
    "type": "color"
  },
  "glass": {
    "value": "rgba({mint.6}, 0.7)",
    "type": "color"
  },
  "inverse": {
    "background": {
      "value": "{mint.0}",
      "type": "color"
    },
    "surface": {
      "value": "{mint.1}",
      "type": "color"
    },
    "border": {
      "value": "{mint.2}",
      "type": "color"
    },
    "on-low": {
      "value": "{mint.3}",
      "type": "color"
    },
    "on-mid": {
      "value": "{mint.4}",
      "type": "color"
    },
    "on": {
      "value": "{mint.7}",
      "type": "color"
    }
  }
}